makewindowsicons/__init__.py
makewindowsicons/__main__.py
makewindowsicons/args.py
makewindowsicons/util.py
makewindowsicons-0.2.0.dist-info/LICENSE
makewindowsicons-0.2.0.dist-info/METADATA
makewindowsicons-0.2.0.dist-info/WHEEL
makewindowsicons-0.2.0.dist-info/RECORD
