Metadata-Version: 2.1
Name: makewindowsicons
Version: 0.2.0
Summary: Easily create all appropriate icon sizes for a Windows app from a single source image
Home-page: https://github.com/djstompzone/MakeWindowsIcons
License: MIT
Author: DJ Stomp
Requires-Python: >=3.10,<4.0
Classifier: License :: OSI Approved :: MIT License
Classifier: Programming Language :: Python :: 3
Classifier: Programming Language :: Python :: 3.10
Classifier: Programming Language :: Python :: 3.11
Classifier: Programming Language :: Python :: 3.12
Requires-Dist: argparse (>=1.4.0,<2.0.0)
Requires-Dist: pillow (>=10.4.0,<11.0.0)
Project-URL: Repository, https://github.com/djstompzone/MakeWindowsIcons
